README.md
setup.py
Flask_API_Docs.egg-info/PKG-INFO
Flask_API_Docs.egg-info/SOURCES.txt
Flask_API_Docs.egg-info/dependency_links.txt
Flask_API_Docs.egg-info/not-zip-safe
Flask_API_Docs.egg-info/requires.txt
Flask_API_Docs.egg-info/top_level.txt
flask_docs/__init__.py