Metadata-Version: 2.1
Name: Flask-API-Docs
Version: 1.3.2
Summary: Web API docs for Flask
Home-page: https://github.com/lyonyang/flask-docs/flask_docs
Author: Lyon Yang
Author-email: lyon.yang@qq.com
Maintainer: Lyon Yang
Maintainer-email: lyon.yang@qq.com
License: BSD
Platform: any
Classifier: License :: OSI Approved :: BSD License
Classifier: Programming Language :: Python
Classifier: Programming Language :: Python :: 3
Classifier: Programming Language :: Python :: 3.4
Classifier: Programming Language :: Python :: 3.5
Classifier: Programming Language :: Python :: 3.6
